love_tell_ai_mcp/__init__.py
love_tell_ai_mcp-0.1.3.dist-info/WHEEL
love_tell_ai_mcp-0.1.3.dist-info/entry_points.txt
love_tell_ai_mcp-0.1.3.dist-info/METADATA
love_tell_ai_mcp-0.1.3.dist-info/RECORD
