Metadata-Version: 2.3
Name: love-tell-ai-mcp
Version: 0.1.3
Summary: love-tell-ai-mcp
Author: splendor023
Author-email: splendor023 <splendor023@gmail.com>
Requires-Dist: dashscope>=1.24.2
Requires-Dist: fastmcp>=2.11.3
Requires-Python: >=3.12
